{
    "users": [
        {
            "username": "Player",
            "preferences": {
                "likedGenres": [
                    "Fantasy"
                ],
                "likedTags": [
                    "Multiplayer",
                    "Capcom",
                    "R18"
                ],
                "favouriteCreators": [
                    "Capcom",
                    "EA Sports"
                ],
                "maxAgeRating": "G",
                "maxPrice": 100.0
            }
        }
    ]
}